typedai/__init__.py
typedai/client.py
typedai/completions.py
typedai/config.py
typedai/errors.py
typedai/messages.py
typedai/models.py
typedai/util.py
eidolon_typedai-0.1.8.dist-info/LICENSE
eidolon_typedai-0.1.8.dist-info/METADATA
eidolon_typedai-0.1.8.dist-info/WHEEL
eidolon_typedai-0.1.8.dist-info/RECORD
