Metadata-Version: 2.1
Name: eidolon-typedai
Version: 0.1.8
Summary: Simplify the OpenAI chat completions api using type hints.
Author: Luke Lalor
Author-email: lukehlalor@gmail.com
Requires-Python: >=3.10,<4.0
Classifier: Programming Language :: Python :: 3
Classifier: Programming Language :: Python :: 3.10
Classifier: Programming Language :: Python :: 3.11
Classifier: Programming Language :: Python :: 3.12
Requires-Dist: openai (>=1.35.13,<2.0.0)
Requires-Dist: pydantic (>=2.8.2,<3.0.0)
Project-URL: Discord, https://discord.gg/8ZQ6z6Z
Project-URL: Github, https://github.com/eidolon-ai/typedai
Project-URL: Website, https://www.eidolonai.com/
